torcher/Torcher.py
torcher/__init__.py
torcher-0.0.4.dist-info/DESCRIPTION.rst
torcher-0.0.4.dist-info/METADATA
torcher-0.0.4.dist-info/RECORD
torcher-0.0.4.dist-info/WHEEL
torcher-0.0.4.dist-info/metadata.json
torcher-0.0.4.dist-info/top_level.txt
