Metadata-Version: 2.0
Name: torcher
Version: 0.0.4
Summary: A pytorch model training util
Home-page: https://github.com/Starangle/torcher
Author: binsu
Author-email: binsu.cs@qq.com
License: UNKNOWN
Platform: UNKNOWN
Classifier: Programming Language :: Python :: 3
Classifier: License :: OSI Approved :: MIT License
Classifier: Operating System :: OS Independent
Requires-Python: >=3.6
